pyrac/__init__.py
pyrac/__main__.py
pyrac/lib.py
pyrac/rac.py
pyrac-0.2.0.dist-info/LICENSE
pyrac-0.2.0.dist-info/METADATA
pyrac-0.2.0.dist-info/WHEEL
pyrac-0.2.0.dist-info/entry_points.txt
pyrac-0.2.0.dist-info/top_level.txt
pyrac-0.2.0.dist-info/RECORD
