Metadata-Version: 2.1
Name: pyrac
Version: 0.2.0
Summary: Python RESTful API Client
Author-email: Kearash <hi@kearash.io>
Project-URL: Homepage, https://github.com/notkearash/pyrac
Project-URL: Bug Tracker, https://github.com/notkearash/pyrac/issues
Classifier: Programming Language :: Python :: 3.10
Classifier: License :: OSI Approved :: MIT License
Classifier: Operating System :: OS Independent
Requires-Python: >=3.10
License-File: LICENSE
Provides-Extra: build
Requires-Dist: build ; extra == 'build'
Requires-Dist: twine ; extra == 'build'
